{"moduleDefinition":{"range":[1,1,1,60],"value":{"type":"normal","normal":{"moduleName":{"range":[1,8,1,20],"value":["Games","Battle"]},"exposingList":{"range":[1,21,1,60],"value":{"type":"explicit","explicit":[{"range":[1,31,1,41],"value":{"type":"function","function":{"name":"battleCard"}}},{"range":[1,43,1,50],"value":{"type":"function","function":{"name":"endTurn"}}},{"range":[1,52,1,59],"value":{"type":"function","function":{"name":"endGame"}}}]}}}}},"imports":[{"range":[3,1,3,32],"value":{"moduleName":{"range":[3,8,3,12],"value":["Card"]},"moduleAlias":null,"exposingList":{"range":[3,13,3,32],"value":{"type":"explicit","explicit":[{"range":[3,23,3,31],"value":{"type":"typeexpose","typeexpose":{"name":"Card","open":[3,27,3,31]}}}]}}}},{"range":[4,1,4,28],"value":{"moduleName":{"range":[4,8,4,12],"value":["Dict"]},"moduleAlias":null,"exposingList":{"range":[4,13,4,28],"value":{"type":"explicit","explicit":[{"range":[4,23,4,27],"value":{"type":"typeOrAlias","typeOrAlias":{"name":"Dict"}}}]}}}},{"range":[5,1,5,36],"value":{"moduleName":{"range":[5,8,5,12],"value":["Game"]},"moduleAlias":null,"exposingList":{"range":[5,13,5,36],"value":{"type":"explicit","explicit":[{"range":[5,23,5,27],"value":{"type":"typeOrAlias","typeOrAlias":{"name":"Game"}}},{"range":[5,29,5,35],"value":{"type":"typeOrAlias","typeOrAlias":{"name":"Player"}}}]}}}},{"range":[6,1,6,26],"value":{"moduleName":{"range":[6,8,6,18],"value":["List","Extra"]},"moduleAlias":{"range":[6,22,6,26],"value":["List"]},"exposingList":null}},{"range":[7,1,7,28],"value":{"moduleName":{"range":[7,8,7,19],"value":["Maybe","Extra"]},"moduleAlias":{"range":[7,23,7,28],"value":["Maybe"]},"exposingList":null}}],"declarations":[{"range":[10,1,64,6],"value":{"type":"function","function":{"documentation":null,"signature":{"range":[10,1,10,23],"value":{"name":{"range":[10,1,10,11],"value":"battleCard"},"typeAnnotation":{"range":[10,14,10,23],"value":{"type":"typed","typed":{"moduleNameAndName":{"range":[10,14,10,18],"value":{"moduleName":[],"name":"List"}},"args":[{"range":[10,19,10,23],"value":{"type":"typed","typed":{"moduleNameAndName":{"range":[10,19,10,23],"value":{"moduleName":[],"name":"Card"}},"args":[]}}}]}}}}},"declaration":{"range":[11,1,64,6],"value":{"name":{"range":[11,1,11,11],"value":"battleCard"},"arguments":[],"expression":{"range":[12,5,64,6],"value":{"type":"list","list":[{"range":[12,7,12,18],"value":{"type":"application","application":[{"range":[12,7,12,15],"value":{"type":"functionOrValue","functionOrValue":{"moduleName":[],"name":"OneClubs"}}},{"range":[12,16,12,18],"value":{"type":"integer","integer":14}}]}},{"range":[13,7,13,17],"value":{"type":"application","application":[{"range":[13,7,13,15],"value":{"type":"functionOrValue","functionOrValue":{"moduleName":[],"name":"TwoClubs"}}},{"range":[13,16,13,17],"value":{"type":"integer","integer":2}}]}},{"range":[14,7,14,19],"value":{"type":"application","application":[{"range":[14,7,14,17],"value":{"type":"functionOrValue","functionOrValue":{"moduleName":[],"name":"ThreeClubs"}}},{"range":[14,18,14,19],"value":{"type":"integer","integer":3}}]}},{"range":[15,7,15,18],"value":{"type":"application","application":[{"range":[15,7,15,16],"value":{"type":"functionOrValue","functionOrValue":{"moduleName":[],"name":"FourClubs"}}},{"range":[15,17,15,18],"value":{"type":"integer","integer":4}}]}},{"range":[16,7,16,18],"value":{"type":"application","application":[{"range":[16,7,16,16],"value":{"type":"functionOrValue","functionOrValue":{"moduleName":[],"name":"FiveClubs"}}},{"range":[16,17,16,18],"value":{"type":"integer","integer":5}}]}},{"range":[17,7,17,17],"value":{"type":"application","application":[{"range":[17,7,17,15],"value":{"type":"functionOrValue","functionOrValue":{"moduleName":[],"name":"SixClubs"}}},{"range":[17,16,17,17],"value":{"type":"integer","integer":6}}]}},{"range":[18,7,18,19],"value":{"type":"application","application":[{"range":[18,7,18,17],"value":{"type":"functionOrValue","functionOrValue":{"moduleName":[],"name":"SevenClubs"}}},{"range":[18,18,18,19],"value":{"type":"integer","integer":7}}]}},{"range":[19,7,19,20],"value":{"type":"application","application":[{"range":[19,7,19,18],"value":{"type":"functionOrValue","functionOrValue":{"moduleName":[],"name":"HeightClubs"}}},{"range":[19,19,19,20],"value":{"type":"integer","integer":8}}]}},{"range":[20,7,20,18],"value":{"type":"application","application":[{"range":[20,7,20,16],"value":{"type":"functionOrValue","functionOrValue":{"moduleName":[],"name":"NiveClubs"}}},{"range":[20,17,20,18],"value":{"type":"integer","integer":9}}]}},{"range":[21,7,21,18],"value":{"type":"application","application":[{"range":[21,7,21,15],"value":{"type":"functionOrValue","functionOrValue":{"moduleName":[],"name":"TenClubs"}}},{"range":[21,16,21,18],"value":{"type":"integer","integer":10}}]}},{"range":[22,7,22,20],"value":{"type":"application","application":[{"range":[22,7,22,17],"value":{"type":"functionOrValue","functionOrValue":{"moduleName":[],"name":"ValetClubs"}}},{"range":[22,18,22,20],"value":{"type":"integer","integer":11}}]}},{"range":[23,7,23,20],"value":{"type":"application","application":[{"range":[23,7,23,17],"value":{"type":"functionOrValue","functionOrValue":{"moduleName":[],"name":"ReineClubs"}}},{"range":[23,18,23,20],"value":{"type":"integer","integer":12}}]}},{"range":[24,7,24,18],"value":{"type":"application","application":[{"range":[24,7,24,15],"value":{"type":"functionOrValue","functionOrValue":{"moduleName":[],"name":"RoiClubs"}}},{"range":[24,16,24,18],"value":{"type":"integer","integer":13}}]}},{"range":[25,7,25,20],"value":{"type":"application","application":[{"range":[25,7,25,17],"value":{"type":"functionOrValue","functionOrValue":{"moduleName":[],"name":"OneDiamond"}}},{"range":[25,18,25,20],"value":{"type":"integer","integer":14}}]}},{"range":[26,7,26,19],"value":{"type":"application","application":[{"range":[26,7,26,17],"value":{"type":"functionOrValue","functionOrValue":{"moduleName":[],"name":"TwoDiamond"}}},{"range":[26,18,26,19],"value":{"type":"integer","integer":2}}]}},{"range":[27,7,27,21],"value":{"type":"application","application":[{"range":[27,7,27,19],"value":{"type":"functionOrValue","functionOrValue":{"moduleName":[],"name":"ThreeDiamond"}}},{"range":[27,20,27,21],"value":{"type":"integer","integer":3}}]}},{"range":[28,7,28,20],"value":{"type":"application","application":[{"range":[28,7,28,18],"value":{"type":"functionOrValue","functionOrValue":{"moduleName":[],"name":"FourDiamond"}}},{"range":[28,19,28,20],"value":{"type":"integer","integer":4}}]}},{"range":[29,7,29,20],"value":{"type":"application","application":[{"range":[29,7,29,18],"value":{"type":"functionOrValue","functionOrValue":{"moduleName":[],"name":"FiveDiamond"}}},{"range":[29,19,29,20],"value":{"type":"integer","integer":5}}]}},{"range":[30,7,30,19],"value":{"type":"application","application":[{"range":[30,7,30,17],"value":{"type":"functionOrValue","functionOrValue":{"moduleName":[],"name":"SixDiamond"}}},{"range":[30,18,30,19],"value":{"type":"integer","integer":6}}]}},{"range":[31,7,31,21],"value":{"type":"application","application":[{"range":[31,7,31,19],"value":{"type":"functionOrValue","functionOrValue":{"moduleName":[],"name":"SevenDiamond"}}},{"range":[31,20,31,21],"value":{"type":"integer","integer":7}}]}},{"range":[32,7,32,22],"value":{"type":"application","application":[{"range":[32,7,32,20],"value":{"type":"functionOrValue","functionOrValue":{"moduleName":[],"name":"HeightDiamond"}}},{"range":[32,21,32,22],"value":{"type":"integer","integer":8}}]}},{"range":[33,7,33,20],"value":{"type":"application","application":[{"range":[33,7,33,18],"value":{"type":"functionOrValue","functionOrValue":{"moduleName":[],"name":"NiveDiamond"}}},{"range":[33,19,33,20],"value":{"type":"integer","integer":9}}]}},{"range":[34,7,34,20],"value":{"type":"application","application":[{"range":[34,7,34,17],"value":{"type":"functionOrValue","functionOrValue":{"moduleName":[],"name":"TenDiamond"}}},{"range":[34,18,34,20],"value":{"type":"integer","integer":10}}]}},{"range":[35,7,35,22],"value":{"type":"application","application":[{"range":[35,7,35,19],"value":{"type":"functionOrValue","functionOrValue":{"moduleName":[],"name":"ValetDiamond"}}},{"range":[35,20,35,22],"value":{"type":"integer","integer":11}}]}},{"range":[36,7,36,22],"value":{"type":"application","application":[{"range":[36,7,36,19],"value":{"type":"functionOrValue","functionOrValue":{"moduleName":[],"name":"ReineDiamond"}}},{"range":[36,20,36,22],"value":{"type":"integer","integer":12}}]}},{"range":[37,7,37,20],"value":{"type":"application","application":[{"range":[37,7,37,17],"value":{"type":"functionOrValue","functionOrValue":{"moduleName":[],"name":"RoiDiamond"}}},{"range":[37,18,37,20],"value":{"type":"integer","integer":13}}]}},{"range":[38,7,38,19],"value":{"type":"application","application":[{"range":[38,7,38,16],"value":{"type":"functionOrValue","functionOrValue":{"moduleName":[],"name":"OneHearts"}}},{"range":[38,17,38,19],"value":{"type":"integer","integer":14}}]}},{"range":[39,7,39,18],"value":{"type":"application","application":[{"range":[39,7,39,16],"value":{"type":"functionOrValue","functionOrValue":{"moduleName":[],"name":"TwoHearts"}}},{"range":[39,17,39,18],"value":{"type":"integer","integer":2}}]}},{"range":[40,7,40,20],"value":{"type":"application","application":[{"range":[40,7,40,18],"value":{"type":"functionOrValue","functionOrValue":{"moduleName":[],"name":"ThreeHearts"}}},{"range":[40,19,40,20],"value":{"type":"integer","integer":3}}]}},{"range":[41,7,41,19],"value":{"type":"application","application":[{"range":[41,7,41,17],"value":{"type":"functionOrValue","functionOrValue":{"moduleName":[],"name":"FourHearts"}}},{"range":[41,18,41,19],"value":{"type":"integer","integer":4}}]}},{"range":[42,7,42,19],"value":{"type":"application","application":[{"range":[42,7,42,17],"value":{"type":"functionOrValue","functionOrValue":{"moduleName":[],"name":"FiveHearts"}}},{"range":[42,18,42,19],"value":{"type":"integer","integer":5}}]}},{"range":[43,7,43,18],"value":{"type":"application","application":[{"range":[43,7,43,16],"value":{"type":"functionOrValue","functionOrValue":{"moduleName":[],"name":"SixHearts"}}},{"range":[43,17,43,18],"value":{"type":"integer","integer":6}}]}},{"range":[44,7,44,20],"value":{"type":"application","application":[{"range":[44,7,44,18],"value":{"type":"functionOrValue","functionOrValue":{"moduleName":[],"name":"SevenHearts"}}},{"range":[44,19,44,20],"value":{"type":"integer","integer":7}}]}},{"range":[45,7,45,21],"value":{"type":"application","application":[{"range":[45,7,45,19],"value":{"type":"functionOrValue","functionOrValue":{"moduleName":[],"name":"HeightHearts"}}},{"range":[45,20,45,21],"value":{"type":"integer","integer":8}}]}},{"range":[46,7,46,19],"value":{"type":"application","application":[{"range":[46,7,46,17],"value":{"type":"functionOrValue","functionOrValue":{"moduleName":[],"name":"NiveHearts"}}},{"range":[46,18,46,19],"value":{"type":"integer","integer":9}}]}},{"range":[47,7,47,19],"value":{"type":"application","application":[{"range":[47,7,47,16],"value":{"type":"functionOrValue","functionOrValue":{"moduleName":[],"name":"TenHearts"}}},{"range":[47,17,47,19],"value":{"type":"integer","integer":10}}]}},{"range":[48,7,48,21],"value":{"type":"application","application":[{"range":[48,7,48,18],"value":{"type":"functionOrValue","functionOrValue":{"moduleName":[],"name":"ValetHearts"}}},{"range":[48,19,48,21],"value":{"type":"integer","integer":11}}]}},{"range":[49,7,49,21],"value":{"type":"application","application":[{"range":[49,7,49,18],"value":{"type":"functionOrValue","functionOrValue":{"moduleName":[],"name":"ReineHearts"}}},{"range":[49,19,49,21],"value":{"type":"integer","integer":12}}]}},{"range":[50,7,50,19],"value":{"type":"application","application":[{"range":[50,7,50,16],"value":{"type":"functionOrValue","functionOrValue":{"moduleName":[],"name":"RoiHearts"}}},{"range":[50,17,50,19],"value":{"type":"integer","integer":13}}]}},{"range":[51,7,51,19],"value":{"type":"application","application":[{"range":[51,7,51,16],"value":{"type":"functionOrValue","functionOrValue":{"moduleName":[],"name":"OneSpades"}}},{"range":[51,17,51,19],"value":{"type":"integer","integer":14}}]}},{"range":[52,7,52,18],"value":{"type":"application","application":[{"range":[52,7,52,16],"value":{"type":"functionOrValue","functionOrValue":{"moduleName":[],"name":"TwoSpades"}}},{"range":[52,17,52,18],"value":{"type":"integer","integer":2}}]}},{"range":[53,7,53,20],"value":{"type":"application","application":[{"range":[53,7,53,18],"value":{"type":"functionOrValue","functionOrValue":{"moduleName":[],"name":"ThreeSpades"}}},{"range":[53,19,53,20],"value":{"type":"integer","integer":3}}]}},{"range":[54,7,54,19],"value":{"type":"application","application":[{"range":[54,7,54,17],"value":{"type":"functionOrValue","functionOrValue":{"moduleName":[],"name":"FourSpades"}}},{"range":[54,18,54,19],"value":{"type":"integer","integer":4}}]}},{"range":[55,7,55,19],"value":{"type":"application","application":[{"range":[55,7,55,17],"value":{"type":"functionOrValue","functionOrValue":{"moduleName":[],"name":"FiveSpades"}}},{"range":[55,18,55,19],"value":{"type":"integer","integer":5}}]}},{"range":[56,7,56,18],"value":{"type":"application","application":[{"range":[56,7,56,16],"value":{"type":"functionOrValue","functionOrValue":{"moduleName":[],"name":"SixSpades"}}},{"range":[56,17,56,18],"value":{"type":"integer","integer":6}}]}},{"range":[57,7,57,20],"value":{"type":"application","application":[{"range":[57,7,57,18],"value":{"type":"functionOrValue","functionOrValue":{"moduleName":[],"name":"SevenSpades"}}},{"range":[57,19,57,20],"value":{"type":"integer","integer":7}}]}},{"range":[58,7,58,21],"value":{"type":"application","application":[{"range":[58,7,58,19],"value":{"type":"functionOrValue","functionOrValue":{"moduleName":[],"name":"HeightSpades"}}},{"range":[58,20,58,21],"value":{"type":"integer","integer":8}}]}},{"range":[59,7,59,19],"value":{"type":"application","application":[{"range":[59,7,59,17],"value":{"type":"functionOrValue","functionOrValue":{"moduleName":[],"name":"NiveSpades"}}},{"range":[59,18,59,19],"value":{"type":"integer","integer":9}}]}},{"range":[60,7,60,19],"value":{"type":"application","application":[{"range":[60,7,60,16],"value":{"type":"functionOrValue","functionOrValue":{"moduleName":[],"name":"TenSpades"}}},{"range":[60,17,60,19],"value":{"type":"integer","integer":10}}]}},{"range":[61,7,61,21],"value":{"type":"application","application":[{"range":[61,7,61,18],"value":{"type":"functionOrValue","functionOrValue":{"moduleName":[],"name":"ValetSpades"}}},{"range":[61,19,61,21],"value":{"type":"integer","integer":11}}]}},{"range":[62,7,62,21],"value":{"type":"application","application":[{"range":[62,7,62,18],"value":{"type":"functionOrValue","functionOrValue":{"moduleName":[],"name":"ReineSpades"}}},{"range":[62,19,62,21],"value":{"type":"integer","integer":12}}]}},{"range":[63,7,63,19],"value":{"type":"application","application":[{"range":[63,7,63,16],"value":{"type":"functionOrValue","functionOrValue":{"moduleName":[],"name":"RoiSpades"}}},{"range":[63,17,63,19],"value":{"type":"integer","integer":13}}]}}]}}}}}}},{"range":[67,1,99,1],"value":{"type":"function","function":{"documentation":null,"signature":{"range":[67,1,67,23],"value":{"name":{"range":[67,1,67,8],"value":"endTurn"},"typeAnnotation":{"range":[67,11,67,23],"value":{"type":"function","function":{"left":{"range":[67,11,67,15],"value":{"type":"typed","typed":{"moduleNameAndName":{"range":[67,11,67,15],"value":{"moduleName":[],"name":"Game"}},"args":[]}}},"right":{"range":[67,19,67,23],"value":{"type":"typed","typed":{"moduleNameAndName":{"range":[67,19,67,23],"value":{"moduleName":[],"name":"Game"}},"args":[]}}}}}}}},"declaration":{"range":[68,1,99,1],"value":{"name":{"range":[68,1,68,8],"value":"endTurn"},"arguments":[{"range":[68,9,68,13],"value":{"type":"var","var":{"value":"game"}}}],"expression":{"range":[69,5,99,1],"value":{"type":"ifBlock","ifBlock":{"clause":{"range":[69,12,69,85],"value":{"type":"application","application":[{"range":[69,12,69,20],"value":{"type":"recordAccess","recordAccess":{"expression":{"range":[69,8,69,12],"value":{"type":"functionOrValue","functionOrValue":{"moduleName":[],"name":"game"}}},"name":{"range":[69,13,69,20],"value":"players"}}}},{"range":[69,21,69,23],"value":{"type":"operator","operator":"|>"}},{"range":[69,24,69,35],"value":{"type":"functionOrValue","functionOrValue":{"moduleName":["Dict"],"name":"values"}}},{"range":[69,36,69,38],"value":{"type":"operator","operator":"|>"}},{"range":[69,39,69,47],"value":{"type":"functionOrValue","functionOrValue":{"moduleName":["List"],"name":"map"}}},{"range":[69,48,69,60],"value":{"type":"recordAccessFunction","recordAccessFunction":".currentCard"}},{"range":[69,61,69,63],"value":{"type":"operator","operator":"|>"}},{"range":[69,64,69,72],"value":{"type":"functionOrValue","functionOrValue":{"moduleName":["List"],"name":"all"}}},{"range":[69,73,69,85],"value":{"type":"functionOrValue","functionOrValue":{"moduleName":["Maybe"],"name":"isJust"}}}]}},"then":{"range":[70,9,95,5],"value":{"type":"let","let":{"declarations":[{"range":[71,13,82,9],"value":{"type":"destructuring","destructuring":{"pattern":{"range":[71,13,71,36],"value":{"type":"tuple","tuple":{"value":[{"range":[71,15,71,26],"value":{"type":"var","var":{"value":"roundWinner"}}},{"range":[71,28,71,34],"value":{"type":"var","var":{"value":"others"}}}]}}},"expression":{"range":[72,21,78,38],"value":{"type":"application","application":[{"range":[72,21,72,29],"value":{"type":"recordAccess","recordAccess":{"expression":{"range":[72,17,72,21],"value":{"type":"functionOrValue","functionOrValue":{"moduleName":[],"name":"game"}}},"name":{"range":[72,22,72,29],"value":"players"}}}},{"range":[73,21,73,23],"value":{"type":"operator","operator":"|>"}},{"range":[73,24,73,35],"value":{"type":"functionOrValue","functionOrValue":{"moduleName":["Dict"],"name":"values"}}},{"range":[74,21,74,23],"value":{"type":"operator","operator":"|>"}},{"range":[74,24,74,32],"value":{"type":"functionOrValue","functionOrValue":{"moduleName":["List"],"name":"map"}}},{"range":[74,33,74,115],"value":{"type":"parenthesized","parenthesized":{"range":[74,34,74,114],"value":{"type":"lambda","lambda":{"patterns":[{"range":[74,35,74,36],"value":{"type":"var","var":{"value":"s"}}}],"expression":{"range":[74,41,74,114],"value":{"type":"application","application":[{"range":[74,41,74,53],"value":{"type":"recordAccess","recordAccess":{"expression":{"range":[74,40,74,41],"value":{"type":"functionOrValue","functionOrValue":{"moduleName":[],"name":"s"}}},"name":{"range":[74,42,74,53],"value":"currentCard"}}}},{"range":[74,54,74,56],"value":{"type":"operator","operator":"|>"}},{"range":[74,57,74,66],"value":{"type":"functionOrValue","functionOrValue":{"moduleName":["Maybe"],"name":"map"}}},{"range":[74,67,74,114],"value":{"type":"parenthesized","parenthesized":{"range":[74,68,74,113],"value":{"type":"lambda","lambda":{"patterns":[{"range":[74,69,74,70],"value":{"type":"var","var":{"value":"a"}}}],"expression":{"range":[74,74,74,113],"value":{"type":"record","record":[{"range":[74,76,74,88],"value":{"field":{"range":[74,76,74,84],"value":"lastCard"},"expression":{"range":[74,87,74,88],"value":{"type":"functionOrValue","functionOrValue":{"moduleName":[],"name":"a"}}}}},{"range":[74,90,74,112],"value":{"field":{"range":[74,90,74,98],"value":"position"},"expression":{"range":[74,102,74,111],"value":{"type":"recordAccess","recordAccess":{"expression":{"range":[74,101,74,102],"value":{"type":"functionOrValue","functionOrValue":{"moduleName":[],"name":"s"}}},"name":{"range":[74,103,74,111],"value":"position"}}}}}}]}}}}}}}]}}}}}}},{"range":[75,21,75,23],"value":{"type":"operator","operator":"|>"}},{"range":[75,24,75,36],"value":{"type":"functionOrValue","functionOrValue":{"moduleName":["Maybe"],"name":"values"}}},{"range":[76,21,76,23],"value":{"type":"operator","operator":"|>"}},{"range":[76,24,76,35],"value":{"type":"functionOrValue","functionOrValue":{"moduleName":["List"],"name":"sortBy"}}},{"range":[76,36,76,65],"value":{"type":"parenthesized","parenthesized":{"range":[76,37,76,64],"value":{"type":"lambda","lambda":{"patterns":[{"range":[76,38,76,39],"value":{"type":"var","var":{"value":"s"}}}],"expression":{"range":[76,43,76,64],"value":{"type":"application","application":[{"range":[76,43,76,53],"value":{"type":"functionOrValue","functionOrValue":{"moduleName":["Card"],"name":"value"}}},{"range":[76,55,76,64],"value":{"type":"recordAccess","recordAccess":{"expression":{"range":[76,54,76,55],"value":{"type":"functionOrValue","functionOrValue":{"moduleName":[],"name":"s"}}},"name":{"range":[76,56,76,64],"value":"lastCard"}}}}]}}}}}}},{"range":[77,21,77,23],"value":{"type":"operator","operator":"|>"}},{"range":[77,24,77,36],"value":{"type":"functionOrValue","functionOrValue":{"moduleName":["List"],"name":"reverse"}}},{"range":[78,21,78,23],"value":{"type":"operator","operator":"|>"}},{"range":[78,24,78,36],"value":{"type":"functionOrValue","functionOrValue":{"moduleName":["List"],"name":"splitAt"}}},{"range":[78,37,78,38],"value":{"type":"integer","integer":1}}]}}}}}],"expression":{"range":[83,9,93,21],"value":{"type":"case","case":{"cases":[{"pattern":{"range":[84,13,84,40],"value":{"type":"named","named":{"qualified":{"moduleName":[],"name":"Just"},"patterns":[{"range":[84,18,84,40],"value":{"type":"record","record":{"value":[{"range":[84,20,84,28],"value":"position"},{"range":[84,30,84,38],"value":"lastCard"}]}}}]}}},"expression":{"range":[85,17,90,18],"value":{"type":"recordUpdate","recordUpdate":{"name":{"range":[85,19,85,23],"value":"game"},"updates":[{"range":[86,23,90,17],"value":{"field":{"range":[86,23,86,30],"value":"players"},"expression":{"range":[87,29,89,94],"value":{"type":"application","application":[{"range":[87,29,87,37],"value":{"type":"recordAccess","recordAccess":{"expression":{"range":[87,25,87,29],"value":{"type":"functionOrValue","functionOrValue":{"moduleName":[],"name":"game"}}},"name":{"range":[87,30,87,37],"value":"players"}}}},{"range":[88,29,88,31],"value":{"type":"operator","operator":"|>"}},{"range":[88,32,88,55],"value":{"type":"functionOrValue","functionOrValue":{"moduleName":[],"name":"addCardsToPlayerDiscard"}}},{"range":[88,56,88,64],"value":{"type":"functionOrValue","functionOrValue":{"moduleName":[],"name":"position"}}},{"range":[88,65,88,113],"value":{"type":"parenthesized","parenthesized":{"range":[88,66,88,112],"value":{"type":"application","application":[{"range":[88,66,88,72],"value":{"type":"functionOrValue","functionOrValue":{"moduleName":[],"name":"others"}}},{"range":[88,74,88,76],"value":{"type":"operator","operator":"|>"}},{"range":[88,77,88,85],"value":{"type":"functionOrValue","functionOrValue":{"moduleName":["List"],"name":"map"}}},{"range":[88,86,88,95],"value":{"type":"recordAccessFunction","recordAccessFunction":".lastCard"}},{"range":[88,96,88,98],"value":{"type":"operator","operator":"|>"}},{"range":[88,99,88,103],"value":{"type":"prefixoperator","prefixoperator":"::"}},{"range":[88,104,88,112],"value":{"type":"functionOrValue","functionOrValue":{"moduleName":[],"name":"lastCard"}}}]}}}},{"range":[89,29,89,31],"value":{"type":"operator","operator":"|>"}},{"range":[89,32,89,40],"value":{"type":"functionOrValue","functionOrValue":{"moduleName":["Dict"],"name":"map"}}},{"range":[89,41,89,94],"value":{"type":"parenthesized","parenthesized":{"range":[89,42,89,93],"value":{"type":"lambda","lambda":{"patterns":[{"range":[89,43,89,44],"value":{"type":"all","all":{}}}],"expression":{"range":[89,48,89,93],"value":{"type":"lambda","lambda":{"patterns":[{"range":[89,49,89,55],"value":{"type":"var","var":{"value":"player"}}}],"expression":{"range":[89,59,89,93],"value":{"type":"recordUpdate","recordUpdate":{"name":{"range":[89,61,89,67],"value":"player"},"updates":[{"range":[89,70,89,92],"value":{"field":{"range":[89,70,89,81],"value":"currentCard"},"expression":{"range":[89,84,89,91],"value":{"type":"functionOrValue","functionOrValue":{"moduleName":[],"name":"Nothing"}}}}}]}}}}}}}}}}}]}}}}]}}}},{"pattern":{"range":[92,13,92,20],"value":{"type":"named","named":{"qualified":{"moduleName":[],"name":"Nothing"},"patterns":[]}}},"expression":{"range":[93,17,93,21],"value":{"type":"functionOrValue","functionOrValue":{"moduleName":[],"name":"game"}}}}],"expression":{"range":[83,14,83,38],"value":{"type":"application","application":[{"range":[83,14,83,25],"value":{"type":"functionOrValue","functionOrValue":{"moduleName":[],"name":"roundWinner"}}},{"range":[83,26,83,28],"value":{"type":"operator","operator":"|>"}},{"range":[83,29,83,38],"value":{"type":"functionOrValue","functionOrValue":{"moduleName":["List"],"name":"head"}}}]}}}}}}}},"else":{"range":[96,9,96,13],"value":{"type":"functionOrValue","functionOrValue":{"moduleName":[],"name":"game"}}}}}}}}}}},{"range":[99,1,109,1],"value":{"type":"function","function":{"documentation":null,"signature":{"range":[99,1,99,30],"value":{"name":{"range":[99,1,99,8],"value":"endGame"},"typeAnnotation":{"range":[99,10,99,30],"value":{"type":"function","function":{"left":{"range":[99,10,99,14],"value":{"type":"typed","typed":{"moduleNameAndName":{"range":[99,10,99,14],"value":{"moduleName":[],"name":"Game"}},"args":[]}}},"right":{"range":[99,18,99,30],"value":{"type":"typed","typed":{"moduleNameAndName":{"range":[99,18,99,23],"value":{"moduleName":[],"name":"Maybe"}},"args":[{"range":[99,24,99,30],"value":{"type":"typed","typed":{"moduleNameAndName":{"range":[99,24,99,30],"value":{"moduleName":[],"name":"Player"}},"args":[]}}}]}}}}}}}},"declaration":{"range":[100,1,109,1],"value":{"name":{"range":[100,1,100,8],"value":"endGame"},"arguments":[{"range":[100,9,100,13],"value":{"type":"var","var":{"value":"game"}}}],"expression":{"range":[101,5,109,1],"value":{"type":"let","let":{"declarations":[{"range":[102,9,103,5],"value":{"type":"function","function":{"documentation":null,"signature":null,"declaration":{"range":[102,9,103,5],"value":{"name":{"range":[102,9,102,16],"value":"isEmpty"},"arguments":[],"expression":{"range":[102,19,103,5],"value":{"type":"lambda","lambda":{"patterns":[{"range":[102,20,102,21],"value":{"type":"var","var":{"value":"p"}}}],"expression":{"range":[102,25,102,102],"value":{"type":"application","application":[{"range":[102,25,102,37],"value":{"type":"functionOrValue","functionOrValue":{"moduleName":["List"],"name":"isEmpty"}}},{"range":[102,39,102,44],"value":{"type":"recordAccess","recordAccess":{"expression":{"range":[102,38,102,39],"value":{"type":"functionOrValue","functionOrValue":{"moduleName":[],"name":"p"}}},"name":{"range":[102,40,102,44],"value":"hand"}}}},{"range":[102,45,102,47],"value":{"type":"operator","operator":"&&"}},{"range":[102,48,102,60],"value":{"type":"functionOrValue","functionOrValue":{"moduleName":["List"],"name":"isEmpty"}}},{"range":[102,62,102,70],"value":{"type":"recordAccess","recordAccess":{"expression":{"range":[102,61,102,62],"value":{"type":"functionOrValue","functionOrValue":{"moduleName":[],"name":"p"}}},"name":{"range":[102,63,102,70],"value":"discard"}}}},{"range":[102,71,102,73],"value":{"type":"operator","operator":"&&"}},{"range":[102,74,102,102],"value":{"type":"parenthesized","parenthesized":{"range":[102,75,102,101],"value":{"type":"application","application":[{"range":[102,75,102,87],"value":{"type":"functionOrValue","functionOrValue":{"moduleName":["Maybe"],"name":"isJust"}}},{"range":[102,89,102,101],"value":{"type":"recordAccess","recordAccess":{"expression":{"range":[102,88,102,89],"value":{"type":"functionOrValue","functionOrValue":{"moduleName":[],"name":"p"}}},"name":{"range":[102,90,102,101],"value":"currentCard"}}}}]}}}}]}}}}}}}}}}],"expression":{"range":[104,5,109,1],"value":{"type":"ifBlock","ifBlock":{"clause":{"range":[104,12,104,55],"value":{"type":"application","application":[{"range":[104,12,104,20],"value":{"type":"recordAccess","recordAccess":{"expression":{"range":[104,8,104,12],"value":{"type":"functionOrValue","functionOrValue":{"moduleName":[],"name":"game"}}},"name":{"range":[104,13,104,20],"value":"players"}}}},{"range":[104,21,104,23],"value":{"type":"operator","operator":"|>"}},{"range":[104,24,104,35],"value":{"type":"functionOrValue","functionOrValue":{"moduleName":["Dict"],"name":"values"}}},{"range":[104,36,104,38],"value":{"type":"operator","operator":"|>"}},{"range":[104,39,104,47],"value":{"type":"functionOrValue","functionOrValue":{"moduleName":["List"],"name":"any"}}},{"range":[104,48,104,55],"value":{"type":"functionOrValue","functionOrValue":{"moduleName":[],"name":"isEmpty"}}}]}},"then":{"range":[105,13,105,90],"value":{"type":"application","application":[{"range":[105,13,105,21],"value":{"type":"recordAccess","recordAccess":{"expression":{"range":[105,9,105,13],"value":{"type":"functionOrValue","functionOrValue":{"moduleName":[],"name":"game"}}},"name":{"range":[105,14,105,21],"value":"players"}}}},{"range":[105,22,105,24],"value":{"type":"operator","operator":"|>"}},{"range":[105,25,105,36],"value":{"type":"functionOrValue","functionOrValue":{"moduleName":["Dict"],"name":"values"}}},{"range":[105,37,105,39],"value":{"type":"operator","operator":"|>"}},{"range":[105,40,105,51],"value":{"type":"functionOrValue","functionOrValue":{"moduleName":["List"],"name":"filter"}}},{"range":[105,52,105,77],"value":{"type":"parenthesized","parenthesized":{"range":[105,53,105,76],"value":{"type":"lambda","lambda":{"patterns":[{"range":[105,54,105,55],"value":{"type":"var","var":{"value":"s"}}}],"expression":{"range":[105,59,105,76],"value":{"type":"application","application":[{"range":[105,59,105,62],"value":{"type":"functionOrValue","functionOrValue":{"moduleName":[],"name":"not"}}},{"range":[105,63,105,65],"value":{"type":"operator","operator":"<|"}},{"range":[105,67,105,74],"value":{"type":"functionOrValue","functionOrValue":{"moduleName":[],"name":"isEmpty"}}},{"range":[105,75,105,76],"value":{"type":"functionOrValue","functionOrValue":{"moduleName":[],"name":"s"}}}]}}}}}}},{"range":[105,78,105,80],"value":{"type":"operator","operator":"|>"}},{"range":[105,81,105,90],"value":{"type":"functionOrValue","functionOrValue":{"moduleName":["List"],"name":"head"}}}]}},"else":{"range":[107,9,107,16],"value":{"type":"functionOrValue","functionOrValue":{"moduleName":[],"name":"Nothing"}}}}}}}}}}}}}},{"range":[109,1,111,135],"value":{"type":"function","function":{"documentation":null,"signature":{"range":[109,1,109,76],"value":{"name":{"range":[109,1,109,24],"value":"removeFromPlayerDiscard"},"typeAnnotation":{"range":[109,27,109,76],"value":{"type":"function","function":{"left":{"range":[109,27,109,30],"value":{"type":"typed","typed":{"moduleNameAndName":{"range":[109,27,109,30],"value":{"moduleName":[],"name":"Int"}},"args":[]}}},"right":{"range":[109,34,109,76],"value":{"type":"function","function":{"left":{"range":[109,34,109,38],"value":{"type":"typed","typed":{"moduleNameAndName":{"range":[109,34,109,38],"value":{"moduleName":[],"name":"Card"}},"args":[]}}},"right":{"range":[109,42,109,76],"value":{"type":"function","function":{"left":{"range":[109,42,109,57],"value":{"type":"typed","typed":{"moduleNameAndName":{"range":[109,42,109,46],"value":{"moduleName":[],"name":"Dict"}},"args":[{"range":[109,47,109,50],"value":{"type":"typed","typed":{"moduleNameAndName":{"range":[109,47,109,50],"value":{"moduleName":[],"name":"Int"}},"args":[]}}},{"range":[109,51,109,57],"value":{"type":"typed","typed":{"moduleNameAndName":{"range":[109,51,109,57],"value":{"moduleName":[],"name":"Player"}},"args":[]}}}]}}},"right":{"range":[109,61,109,76],"value":{"type":"typed","typed":{"moduleNameAndName":{"range":[109,61,109,65],"value":{"moduleName":[],"name":"Dict"}},"args":[{"range":[109,66,109,69],"value":{"type":"typed","typed":{"moduleNameAndName":{"range":[109,66,109,69],"value":{"moduleName":[],"name":"Int"}},"args":[]}}},{"range":[109,70,109,76],"value":{"type":"typed","typed":{"moduleNameAndName":{"range":[109,70,109,76],"value":{"moduleName":[],"name":"Player"}},"args":[]}}}]}}}}}}}}}}}}}},"declaration":{"range":[110,1,111,135],"value":{"name":{"range":[110,1,110,24],"value":"removeFromPlayerDiscard"},"arguments":[{"range":[110,25,110,27],"value":{"type":"var","var":{"value":"id"}}},{"range":[110,28,110,32],"value":{"type":"var","var":{"value":"card"}}},{"range":[110,33,110,40],"value":{"type":"var","var":{"value":"players"}}}],"expression":{"range":[111,5,111,135],"value":{"type":"application","application":[{"range":[111,5,111,16],"value":{"type":"functionOrValue","functionOrValue":{"moduleName":["Dict"],"name":"update"}}},{"range":[111,17,111,19],"value":{"type":"functionOrValue","functionOrValue":{"moduleName":[],"name":"id"}}},{"range":[111,20,111,127],"value":{"type":"parenthesized","parenthesized":{"range":[111,21,111,126],"value":{"type":"lambda","lambda":{"patterns":[{"range":[111,22,111,29],"value":{"type":"var","var":{"value":"mPlayer"}}}],"expression":{"range":[111,33,111,126],"value":{"type":"application","application":[{"range":[111,33,111,40],"value":{"type":"functionOrValue","functionOrValue":{"moduleName":[],"name":"mPlayer"}}},{"range":[111,41,111,43],"value":{"type":"operator","operator":"|>"}},{"range":[111,44,111,53],"value":{"type":"functionOrValue","functionOrValue":{"moduleName":["Maybe"],"name":"map"}}},{"range":[111,54,111,126],"value":{"type":"parenthesized","parenthesized":{"range":[111,55,111,125],"value":{"type":"lambda","lambda":{"patterns":[{"range":[111,56,111,62],"value":{"type":"var","var":{"value":"player"}}}],"expression":{"range":[111,66,111,125],"value":{"type":"application","application":[{"range":[111,66,111,72],"value":{"type":"functionOrValue","functionOrValue":{"moduleName":[],"name":"player"}}},{"range":[111,73,111,75],"value":{"type":"operator","operator":"|>"}},{"range":[111,76,111,91],"value":{"type":"functionOrValue","functionOrValue":{"moduleName":["Game"],"name":"setDiscard"}}},{"range":[111,92,111,125],"value":{"type":"parenthesized","parenthesized":{"range":[111,93,111,124],"value":{"type":"application","application":[{"range":[111,93,111,104],"value":{"type":"functionOrValue","functionOrValue":{"moduleName":["List"],"name":"remove"}}},{"range":[111,105,111,109],"value":{"type":"functionOrValue","functionOrValue":{"moduleName":[],"name":"card"}}},{"range":[111,116,111,124],"value":{"type":"recordAccess","recordAccess":{"expression":{"range":[111,110,111,116],"value":{"type":"functionOrValue","functionOrValue":{"moduleName":[],"name":"player"}}},"name":{"range":[111,117,111,124],"value":"discard"}}}}]}}}}]}}}}}}}]}}}}}}},{"range":[111,128,111,135],"value":{"type":"functionOrValue","functionOrValue":{"moduleName":[],"name":"players"}}}]}}}}}}},{"range":[114,1,116,127],"value":{"type":"function","function":{"documentation":null,"signature":{"range":[114,1,114,81],"value":{"name":{"range":[114,1,114,24],"value":"addCardsToPlayerDiscard"},"typeAnnotation":{"range":[114,27,114,81],"value":{"type":"function","function":{"left":{"range":[114,27,114,30],"value":{"type":"typed","typed":{"moduleNameAndName":{"range":[114,27,114,30],"value":{"moduleName":[],"name":"Int"}},"args":[]}}},"right":{"range":[114,34,114,81],"value":{"type":"function","function":{"left":{"range":[114,34,114,43],"value":{"type":"typed","typed":{"moduleNameAndName":{"range":[114,34,114,38],"value":{"moduleName":[],"name":"List"}},"args":[{"range":[114,39,114,43],"value":{"type":"typed","typed":{"moduleNameAndName":{"range":[114,39,114,43],"value":{"moduleName":[],"name":"Card"}},"args":[]}}}]}}},"right":{"range":[114,47,114,81],"value":{"type":"function","function":{"left":{"range":[114,47,114,62],"value":{"type":"typed","typed":{"moduleNameAndName":{"range":[114,47,114,51],"value":{"moduleName":[],"name":"Dict"}},"args":[{"range":[114,52,114,55],"value":{"type":"typed","typed":{"moduleNameAndName":{"range":[114,52,114,55],"value":{"moduleName":[],"name":"Int"}},"args":[]}}},{"range":[114,56,114,62],"value":{"type":"typed","typed":{"moduleNameAndName":{"range":[114,56,114,62],"value":{"moduleName":[],"name":"Player"}},"args":[]}}}]}}},"right":{"range":[114,66,114,81],"value":{"type":"typed","typed":{"moduleNameAndName":{"range":[114,66,114,70],"value":{"moduleName":[],"name":"Dict"}},"args":[{"range":[114,71,114,74],"value":{"type":"typed","typed":{"moduleNameAndName":{"range":[114,71,114,74],"value":{"moduleName":[],"name":"Int"}},"args":[]}}},{"range":[114,75,114,81],"value":{"type":"typed","typed":{"moduleNameAndName":{"range":[114,75,114,81],"value":{"moduleName":[],"name":"Player"}},"args":[]}}}]}}}}}}}}}}}}}},"declaration":{"range":[115,1,116,127],"value":{"name":{"range":[115,1,115,24],"value":"addCardsToPlayerDiscard"},"arguments":[{"range":[115,25,115,27],"value":{"type":"var","var":{"value":"id"}}},{"range":[115,28,115,33],"value":{"type":"var","var":{"value":"cards"}}},{"range":[115,34,115,41],"value":{"type":"var","var":{"value":"players"}}}],"expression":{"range":[116,5,116,127],"value":{"type":"application","application":[{"range":[116,5,116,16],"value":{"type":"functionOrValue","functionOrValue":{"moduleName":["Dict"],"name":"update"}}},{"range":[116,17,116,19],"value":{"type":"functionOrValue","functionOrValue":{"moduleName":[],"name":"id"}}},{"range":[116,20,116,119],"value":{"type":"parenthesized","parenthesized":{"range":[116,21,116,118],"value":{"type":"lambda","lambda":{"patterns":[{"range":[116,22,116,29],"value":{"type":"var","var":{"value":"mPlayer"}}}],"expression":{"range":[116,33,116,118],"value":{"type":"application","application":[{"range":[116,33,116,40],"value":{"type":"functionOrValue","functionOrValue":{"moduleName":[],"name":"mPlayer"}}},{"range":[116,41,116,43],"value":{"type":"operator","operator":"|>"}},{"range":[116,44,116,53],"value":{"type":"functionOrValue","functionOrValue":{"moduleName":["Maybe"],"name":"map"}}},{"range":[116,54,116,118],"value":{"type":"parenthesized","parenthesized":{"range":[116,55,116,117],"value":{"type":"lambda","lambda":{"patterns":[{"range":[116,56,116,62],"value":{"type":"var","var":{"value":"player"}}}],"expression":{"range":[116,66,116,117],"value":{"type":"application","application":[{"range":[116,66,116,72],"value":{"type":"functionOrValue","functionOrValue":{"moduleName":[],"name":"player"}}},{"range":[116,73,116,75],"value":{"type":"operator","operator":"|>"}},{"range":[116,76,116,91],"value":{"type":"functionOrValue","functionOrValue":{"moduleName":["Game"],"name":"setDiscard"}}},{"range":[116,92,116,117],"value":{"type":"parenthesized","parenthesized":{"range":[116,93,116,116],"value":{"type":"application","application":[{"range":[116,93,116,98],"value":{"type":"functionOrValue","functionOrValue":{"moduleName":[],"name":"cards"}}},{"range":[116,99,116,101],"value":{"type":"operator","operator":"++"}},{"range":[116,108,116,116],"value":{"type":"recordAccess","recordAccess":{"expression":{"range":[116,102,116,108],"value":{"type":"functionOrValue","functionOrValue":{"moduleName":[],"name":"player"}}},"name":{"range":[116,109,116,116],"value":"discard"}}}}]}}}}]}}}}}}}]}}}}}}},{"range":[116,120,116,127],"value":{"type":"functionOrValue","functionOrValue":{"moduleName":[],"name":"players"}}}]}}}}}}}],"comments":[{"range":[81,13,81,44],"value":"-- _ = Debug.log \"othe\" players"},{"range":[80,13,80,141],"value":"-- players = List.foldl (\\{position , lastCard} -> \\dict -> removeFromPlayerDiscard position lastCard dict ) game.players others"}]}